[{"lat":48.5169,"lon":-123.33628,"speed_ms":0.327,"direction_deg":319.6},{"lat":48.51227,"lon":-123.34331,"speed_ms":0.285,"direction_deg":316.6},{"lat":48.52399,"lon":-123.33983,"speed_ms":0.347,"direction_deg":330.7},{"lat":48.53121,"lon":-123.34163,"speed_ms":0.372,"direction_deg":341.4},{"lat":48.51873,"lon":-123.34969,"speed_ms":0.266,"direction_deg":327.9},{"lat":48.54108,"lon":-123.33377,"speed_ms":0.454,"direction_deg":337.7},{"lat":48.52687,"lon":-123.35319,"speed_ms":0.284,"direction_deg":343.3},{"lat":48.53738,"lon":-123.342,"speed_ms":0.406,"direction_deg":344.9},{"lat":48.53407,"lon":-123.35225,"speed_ms":0.333,"direction_deg":352.6},{"lat":48.54681,"lon":-123.33692,"speed_ms":0.501,"direction_deg":340.1},{"lat":48.54257,"lon":-123.34233,"speed_ms":0.452,"direction_deg":344.0},{"lat":48.5402,"lon":-123.3511,"speed_ms":0.386,"direction_deg":354.3},{"lat":48.56412,"lon":-123.33589,"speed_ms":0.524,"direction_deg":338.8},{"lat":48.5589,"lon":-123.3394,"speed_ms":0.59,"direction_deg":344.4},{"lat":48.55304,"lon":-123.33991,"speed_ms":0.562,"direction_deg":342.4},{"lat":48.54732,"lon":-123.34885,"speed_ms":0.473,"direction_deg":349.6},{"lat":48.56907,"lon":-123.34592,"speed_ms":0.625,"direction_deg":339.6},{"lat":48.56223,"lon":-123.34451,"speed_ms":0.6,"direction_deg":346.7},{"lat":48.55699,"lon":-123.34779,"speed_ms":0.615,"direction_deg":348.8},{"lat":48.55254,"lon":-123.34764,"speed_ms":0.561,"direction_deg":346.5},{"lat":48.55254,"lon":-123.35354,"speed_ms":0.48,"direction_deg":353.2},{"lat":48.57696,"lon":-123.34263,"speed_ms":0.445,"direction_deg":339.7},{"lat":48.57501,"lon":-123.35419,"speed_ms":0.611,"direction_deg":341.5},{"lat":48.56853,"lon":-123.3571,"speed_ms":0.427,"direction_deg":349.3},{"lat":48.56206,"lon":-123.35348,"speed_ms":0.497,"direction_deg":350.1},{"lat":48.55672,"lon":-123.35528,"speed_ms":0.52,"direction_deg":352.9},{"lat":48.5827,"lon":-123.35351,"speed_ms":0.688,"direction_deg":340.1},{"lat":48.58916,"lon":-123.35827,"speed_ms":0.841,"direction_deg":336.6},{"lat":48.59455,"lon":-123.361,"speed_ms":0.932,"direction_deg":342.7},{"lat":48.60663,"lon":-123.33465,"speed_ms":0.657,"direction_deg":318.7},{"lat":48.59669,"lon":-123.35567,"speed_ms":0.622,"direction_deg":343.5},{"lat":48.59933,"lon":-123.36219,"speed_ms":0.86,"direction_deg":340.4},{"lat":48.61283,"lon":-123.33929,"speed_ms":0.834,"direction_deg":314.4},{"lat":48.60834,"lon":-123.34206,"speed_ms":0.536,"direction_deg":308.7},{"lat":48.60448,"lon":-123.363,"speed_ms":0.636,"direction_deg":318.3},{"lat":48.60032,"lon":-123.36937,"speed_ms":0.513,"direction_deg":309.4},{"lat":48.61883,"lon":-123.33548,"speed_ms":0.766,"direction_deg":317.5},{"lat":48.61815,"lon":-123.34489,"speed_ms":0.731,"direction_deg":318.1},{"lat":48.61119,"lon":-123.34786,"speed_ms":0.457,"direction_deg":313.8},{"lat":48.60673,"lon":-123.3733,"speed_ms":0.642,"direction_deg":310.6},{"lat":48.60033,"lon":-123.37812,"speed_ms":0.466,"direction_deg":294.0},{"lat":48.59618,"lon":-123.37402,"speed_ms":0.51,"direction_deg":265.7},{"lat":48.62444,"lon":-123.34149,"speed_ms":0.702,"direction_deg":325.4},{"lat":48.62395,"lon":-123.35256,"speed_ms":0.633,"direction_deg":321.3},{"lat":48.61619,"lon":-123.35087,"speed_ms":0.461,"direction_deg":317.0},{"lat":48.61453,"lon":-123.37272,"speed_ms":0.612,"direction_deg":321.3},{"lat":48.6113,"lon":-123.37253,"speed_ms":0.68,"direction_deg":311.2},{"lat":48.61244,"lon":-123.37967,"speed_ms":0.63,"direction_deg":330.6},{"lat":48.6057,"lon":-123.38411,"speed_ms":0.506,"direction_deg":319.6},{"lat":48.63028,"lon":-123.33727,"speed_ms":0.504,"direction_deg":332.1},{"lat":48.63053,"lon":-123.34623,"speed_ms":0.67,"direction_deg":337.1},{"lat":48.63065,"lon":-123.35375,"speed_ms":0.568,"direction_deg":336.4},{"lat":48.62846,"lon":-123.36104,"speed_ms":0.454,"direction_deg":338.9},{"lat":48.62296,"lon":-123.36279,"speed_ms":0.362,"direction_deg":323.7},{"lat":48.61893,"lon":-123.37852,"speed_ms":0.717,"direction_deg":352.1},{"lat":48.61777,"lon":-123.38721,"speed_ms":0.557,"direction_deg":350.6},{"lat":48.61187,"lon":-123.3883,"speed_ms":0.595,"direction_deg":335.6},{"lat":48.60814,"lon":-123.39202,"speed_ms":0.432,"direction_deg":335.0},{"lat":48.63723,"lon":-123.34177,"speed_ms":0.485,"direction_deg":351.2},{"lat":48.63518,"lon":-123.34975,"speed_ms":0.601,"direction_deg":351.0},{"lat":48.63559,"lon":-123.3587,"speed_ms":0.539,"direction_deg":350.4},{"lat":48.63227,"lon":-123.36773,"speed_ms":0.428,"direction_deg":353.6},{"lat":48.62658,"lon":-123.3712,"speed_ms":0.358,"direction_deg":359.6},{"lat":48.62156,"lon":-123.37,"speed_ms":0.279,"direction_deg":7.7},{"lat":48.62217,"lon":-123.37833,"speed_ms":0.454,"direction_deg":9.4},{"lat":48.62419,"lon":-123.38861,"speed_ms":0.423,"direction_deg":354.6},{"lat":48.61408,"lon":-123.39648,"speed_ms":0.413,"direction_deg":343.8},{"lat":48.64117,"lon":-123.34815,"speed_ms":0.529,"direction_deg":356.9},{"lat":48.64298,"lon":-123.36046,"speed_ms":0.533,"direction_deg":357.9},{"lat":48.63808,"lon":-123.36944,"speed_ms":0.468,"direction_deg":0.0},{"lat":48.63298,"lon":-123.37835,"speed_ms":0.393,"direction_deg":6.0},{"lat":48.62721,"lon":-123.38076,"speed_ms":0.403,"direction_deg":3.6},{"lat":48.62976,"lon":-123.38732,"speed_ms":0.386,"direction_deg":1.9},{"lat":48.62856,"lon":-123.39739,"speed_ms":0.283,"direction_deg":359.1},{"lat":48.64876,"lon":-123.35197,"speed_ms":0.602,"direction_deg":358.7},{"lat":48.64942,"lon":-123.36393,"speed_ms":0.517,"direction_deg":1.6},{"lat":48.64482,"lon":-123.37182,"speed_ms":0.48,"direction_deg":4.1},{"lat":48.64021,"lon":-123.38044,"speed_ms":0.439,"direction_deg":9.3},{"lat":48.63591,"lon":-123.39048,"speed_ms":0.372,"direction_deg":11.3},{"lat":48.65399,"lon":-123.34475,"speed_ms":0.409,"direction_deg":9.5},{"lat":48.65442,"lon":-123.35797,"speed_ms":0.557,"direction_deg":6.1},{"lat":48.65411,"lon":-123.367,"speed_ms":0.487,"direction_deg":5.0},{"lat":48.65109,"lon":-123.37402,"speed_ms":0.478,"direction_deg":4.5},{"lat":48.64706,"lon":-123.38331,"speed_ms":0.467,"direction_deg":10.2},{"lat":48.64216,"lon":-123.38921,"speed_ms":0.392,"direction_deg":18.5},{"lat":48.65369,"lon":-123.34071,"speed_ms":0.252,"direction_deg":46.0},{"lat":48.65919,"lon":-123.34326,"speed_ms":0.519,"direction_deg":14.4},{"lat":48.66081,"lon":-123.35407,"speed_ms":0.631,"direction_deg":10.9},{"lat":48.65906,"lon":-123.36508,"speed_ms":0.501,"direction_deg":10.1},{"lat":48.65686,"lon":-123.37412,"speed_ms":0.467,"direction_deg":3.8},{"lat":48.65353,"lon":-123.38305,"speed_ms":0.459,"direction_deg":4.9},{"lat":48.65492,"lon":-123.33462,"speed_ms":0.172,"direction_deg":355.0},{"lat":48.65774,"lon":-123.33712,"speed_ms":0.361,"direction_deg":358.3},{"lat":48.66211,"lon":-123.33714,"speed_ms":0.452,"direction_deg":6.8},{"lat":48.66612,"lon":-123.34655,"speed_ms":0.704,"direction_deg":14.8},{"lat":48.66709,"lon":-123.35647,"speed_ms":0.673,"direction_deg":21.6},{"lat":48.66442,"lon":-123.36287,"speed_ms":0.565,"direction_deg":16.4},{"lat":48.66415,"lon":-123.37371,"speed_ms":0.467,"direction_deg":14.2},{"lat":48.65933,"lon":-123.38305,"speed_ms":0.458,"direction_deg":1.1},{"lat":48.66703,"lon":-123.33863,"speed_ms":0.426,"direction_deg":3.6},{"lat":48.67281,"lon":-123.34372,"speed_ms":0.659,"direction_deg":2.4},{"lat":48.67235,"lon":-123.3537,"speed_ms":0.684,"direction_deg":18.2},{"lat":48.67092,"lon":-123.36582,"speed_ms":0.5,"direction_deg":30.1},{"lat":48.67284,"lon":-123.37887,"speed_ms":0.473,"direction_deg":37.1},{"lat":48.66508,"lon":-123.38474,"speed_ms":0.405,"direction_deg":0.3},{"lat":48.6738,"lon":-123.33414,"speed_ms":0.676,"direction_deg":338.6},{"lat":48.67873,"lon":-123.339,"speed_ms":0.637,"direction_deg":349.4},{"lat":48.67848,"lon":-123.34977,"speed_ms":0.692,"direction_deg":358.0},{"lat":48.67824,"lon":-123.36111,"speed_ms":0.662,"direction_deg":28.5},{"lat":48.68032,"lon":-123.37339,"speed_ms":0.561,"direction_deg":44.0},{"lat":48.67059,"lon":-123.38902,"speed_ms":0.274,"direction_deg":10.9},{"lat":48.68479,"lon":-123.34516,"speed_ms":0.633,"direction_deg":346.7},{"lat":48.6839,"lon":-123.35664,"speed_ms":0.694,"direction_deg":1.3},{"lat":48.68314,"lon":-123.36909,"speed_ms":0.472,"direction_deg":23.2},{"lat":48.6924,"lon":-123.33919,"speed_ms":0.494,"direction_deg":346.4},{"lat":48.69062,"lon":-123.35264,"speed_ms":0.65,"direction_deg":341.1},{"lat":48.68713,"lon":-123.36306,"speed_ms":0.471,"direction_deg":334.8},{"lat":48.70067,"lon":-123.33903,"speed_ms":0.444,"direction_deg":328.1},{"lat":48.69854,"lon":-123.34979,"speed_ms":0.513,"direction_deg":329.7},{"lat":48.6959,"lon":-123.36152,"speed_ms":0.669,"direction_deg":325.2},{"lat":48.69386,"lon":-123.37101,"speed_ms":0.721,"direction_deg":308.8},{"lat":48.70785,"lon":-123.3467,"speed_ms":0.402,"direction_deg":322.5},{"lat":48.70353,"lon":-123.36059,"speed_ms":0.489,"direction_deg":310.6},{"lat":48.69972,"lon":-123.37131,"speed_ms":0.643,"direction_deg":300.1},{"lat":48.69572,"lon":-123.37874,"speed_ms":0.739,"direction_deg":289.6},{"lat":48.69218,"lon":-123.37899,"speed_ms":0.6,"direction_deg":287.0},{"lat":48.71438,"lon":-123.33658,"speed_ms":0.421,"direction_deg":333.8},{"lat":48.71804,"lon":-123.3512,"speed_ms":0.369,"direction_deg":338.8},{"lat":48.71216,"lon":-123.36107,"speed_ms":0.378,"direction_deg":301.6},{"lat":48.70781,"lon":-123.37416,"speed_ms":0.672,"direction_deg":294.3},{"lat":48.70052,"lon":-123.38178,"speed_ms":0.524,"direction_deg":289.8},{"lat":48.71984,"lon":-123.33841,"speed_ms":0.545,"direction_deg":351.3},{"lat":48.72409,"lon":-123.34306,"speed_ms":0.565,"direction_deg":358.1},{"lat":48.72277,"lon":-123.363,"speed_ms":0.347,"direction_deg":0.4},{"lat":48.71854,"lon":-123.36555,"speed_ms":0.224,"direction_deg":326.6},{"lat":48.71393,"lon":-123.38213,"speed_ms":0.624,"direction_deg":302.1},{"lat":48.70746,"lon":-123.38775,"speed_ms":0.733,"direction_deg":300.0},{"lat":48.70016,"lon":-123.3929,"speed_ms":0.436,"direction_deg":289.1},{"lat":48.69293,"lon":-123.39885,"speed_ms":0.382,"direction_deg":278.8},{"lat":48.72861,"lon":-123.33564,"speed_ms":0.635,"direction_deg":1.4},{"lat":48.73006,"lon":-123.34682,"speed_ms":0.659,"direction_deg":357.2},{"lat":48.71421,"lon":-123.39438,"speed_ms":0.695,"direction_deg":309.8},{"lat":48.70692,"lon":-123.39752,"speed_ms":0.471,"direction_deg":319.0},{"lat":48.691,"lon":-123.41145,"speed_ms":0.356,"direction_deg":285.9},{"lat":48.68899,"lon":-123.40479,"speed_ms":0.233,"direction_deg":279.9},{"lat":48.73466,"lon":-123.33734,"speed_ms":0.518,"direction_deg":358.8},{"lat":48.73525,"lon":-123.35027,"speed_ms":0.581,"direction_deg":348.5},{"lat":48.7228,"lon":-123.39437,"speed_ms":0.369,"direction_deg":311.6},{"lat":48.7169,"lon":-123.40523,"speed_ms":0.471,"direction_deg":296.7},{"lat":48.7114,"lon":-123.4026,"speed_ms":0.561,"direction_deg":316.3},{"lat":48.69316,"lon":-123.41821,"speed_ms":0.518,"direction_deg":301.2},{"lat":48.73886,"lon":-123.3362,"speed_ms":0.412,"direction_deg":342.9},{"lat":48.73965,"lon":-123.34314,"speed_ms":0.408,"direction_deg":336.0},{"lat":48.74029,"lon":-123.35488,"speed_ms":0.377,"direction_deg":327.9},{"lat":48.73936,"lon":-123.36558,"speed_ms":0.26,"direction_deg":307.8},{"lat":48.72978,"lon":-123.40321,"speed_ms":0.209,"direction_deg":270.7},{"lat":48.72312,"lon":-123.40447,"speed_ms":0.288,"direction_deg":288.9},{"lat":48.72341,"lon":-123.41572,"speed_ms":0.375,"direction_deg":259.7},{"lat":48.69625,"lon":-123.42603,"speed_ms":0.58,"direction_deg":300.0},{"lat":48.74606,"lon":-123.34739,"speed_ms":0.302,"direction_deg":319.1},{"lat":48.74672,"lon":-123.36228,"speed_ms":0.242,"direction_deg":308.3},{"lat":48.73577,"lon":-123.36825,"speed_ms":0.222,"direction_deg":299.4},{"lat":48.73334,"lon":-123.41564,"speed_ms":0.238,"direction_deg":245.1},{"lat":48.72452,"lon":-123.43034,"speed_ms":0.469,"direction_deg":248.5},{"lat":48.71552,"lon":-123.4243,"speed_ms":0.502,"direction_deg":258.9},{"lat":48.71053,"lon":-123.41735,"speed_ms":0.363,"direction_deg":259.4},{"lat":48.70503,"lon":-123.42544,"speed_ms":0.428,"direction_deg":296.8},{"lat":48.69922,"lon":-123.43196,"speed_ms":0.539,"direction_deg":307.7},{"lat":48.75229,"lon":-123.33859,"speed_ms":0.322,"direction_deg":322.5},{"lat":48.75363,"lon":-123.35346,"speed_ms":0.258,"direction_deg":327.4},{"lat":48.73649,"lon":-123.42317,"speed_ms":0.194,"direction_deg":237.1},{"lat":48.73008,"lon":-123.43447,"speed_ms":0.405,"direction_deg":259.6},{"lat":48.72706,"lon":-123.4407,"speed_ms":0.435,"direction_deg":258.7},{"lat":48.71865,"lon":-123.43757,"speed_ms":0.529,"direction_deg":249.1},{"lat":48.71035,"lon":-123.43332,"speed_ms":0.443,"direction_deg":261.8},{"lat":48.70908,"lon":-123.42203,"speed_ms":0.334,"direction_deg":267.5},{"lat":48.70433,"lon":-123.43489,"speed_ms":0.388,"direction_deg":280.6},{"lat":48.70102,"lon":-123.44013,"speed_ms":0.306,"direction_deg":277.1},{"lat":48.761,"lon":-123.34384,"speed_ms":0.343,"direction_deg":337.3},{"lat":48.76188,"lon":-123.35967,"speed_ms":0.269,"direction_deg":350.8},{"lat":48.72711,"lon":-123.44814,"speed_ms":0.375,"direction_deg":254.5},{"lat":48.721,"lon":-123.44957,"speed_ms":0.479,"direction_deg":242.1},{"lat":48.71329,"lon":-123.44583,"speed_ms":0.514,"direction_deg":249.0},{"lat":48.70622,"lon":-123.44451,"speed_ms":0.488,"direction_deg":254.1},{"lat":48.76911,"lon":-123.34991,"speed_ms":0.418,"direction_deg":347.5},{"lat":48.76879,"lon":-123.36063,"speed_ms":0.412,"direction_deg":3.5},{"lat":48.72615,"lon":-123.45572,"speed_ms":0.369,"direction_deg":246.1},{"lat":48.72104,"lon":-123.46065,"speed_ms":0.453,"direction_deg":246.5},{"lat":48.71392,"lon":-123.45786,"speed_ms":0.537,"direction_deg":241.6},{"lat":48.70983,"lon":-123.45092,"speed_ms":0.473,"direction_deg":245.8},{"lat":48.70562,"lon":-123.45652,"speed_ms":0.493,"direction_deg":251.5},{"lat":48.77829,"lon":-123.34529,"speed_ms":0.516,"direction_deg":348.3},{"lat":48.77453,"lon":-123.3573,"speed_ms":0.533,"direction_deg":354.6},{"lat":48.77208,"lon":-123.36613,"speed_ms":0.445,"direction_deg":7.1},{"lat":48.71799,"lon":-123.46851,"speed_ms":0.515,"direction_deg":255.1},{"lat":48.70965,"lon":-123.4713,"speed_ms":0.532,"direction_deg":250.6},{"lat":48.70142,"lon":-123.46788,"speed_ms":0.475,"direction_deg":254.0},{"lat":48.78569,"lon":-123.33832,"speed_ms":0.52,"direction_deg":345.0},{"lat":48.78712,"lon":-123.3514,"speed_ms":0.492,"direction_deg":343.3},{"lat":48.78031,"lon":-123.35702,"speed_ms":0.522,"direction_deg":348.5},{"lat":48.77696,"lon":-123.36607,"speed_ms":0.398,"direction_deg":345.9},{"lat":48.71603,"lon":-123.47751,"speed_ms":0.486,"direction_deg":262.6},{"lat":48.71082,"lon":-123.48554,"speed_ms":0.493,"direction_deg":258.6},{"lat":48.70171,"lon":-123.48377,"speed_ms":0.406,"direction_deg":251.1},{"lat":48.79417,"lon":-123.33866,"speed_ms":0.467,"direction_deg":344.5},{"lat":48.79608,"lon":-123.35392,"speed_ms":0.431,"direction_deg":339.3},{"lat":48.79125,"lon":-123.36167,"speed_ms":0.501,"direction_deg":332.9},{"lat":48.78501,"lon":-123.36523,"speed_ms":0.561,"direction_deg":335.9},{"lat":48.71505,"lon":-123.48678,"speed_ms":0.498,"direction_deg":271.4},{"lat":48.71489,"lon":-123.49502,"speed_ms":0.294,"direction_deg":294.9},{"lat":48.70792,"lon":-123.49727,"speed_ms":0.362,"direction_deg":279.1},{"lat":48.69964,"lon":-123.50128,"speed_ms":0.205,"direction_deg":275.9},{"lat":48.69303,"lon":-123.49154,"speed_ms":0.184,"direction_deg":236.1},{"lat":48.80318,"lon":-123.3452,"speed_ms":0.427,"direction_deg":350.5},{"lat":48.80331,"lon":-123.36,"speed_ms":0.395,"direction_deg":326.1},{"lat":48.79675,"lon":-123.36589,"speed_ms":0.505,"direction_deg":323.6},{"lat":48.79172,"lon":-123.37209,"speed_ms":0.54,"direction_deg":324.0},{"lat":48.7141,"lon":-123.50851,"speed_ms":0.411,"direction_deg":310.6},{"lat":48.70571,"lon":-123.50958,"speed_ms":0.292,"direction_deg":305.6},{"lat":48.69821,"lon":-123.52038,"speed_ms":0.212,"direction_deg":316.6},{"lat":48.96229,"lon":-123.40194,"speed_ms":0.246,"direction_deg":311.1},{"lat":48.80761,"lon":-123.33366,"speed_ms":0.508,"direction_deg":356.4},{"lat":48.81215,"lon":-123.34412,"speed_ms":0.487,"direction_deg":1.7},{"lat":48.80812,"lon":-123.35292,"speed_ms":0.373,"direction_deg":357.6},{"lat":48.80768,"lon":-123.36924,"speed_ms":0.474,"direction_deg":307.3},{"lat":48.80172,"lon":-123.37392,"speed_ms":0.562,"direction_deg":309.3},{"lat":48.79667,"lon":-123.3735,"speed_ms":0.566,"direction_deg":317.7},{"lat":48.79607,"lon":-123.38101,"speed_ms":0.525,"direction_deg":315.0},{"lat":48.78915,"lon":-123.38289,"speed_ms":0.468,"direction_deg":317.2},{"lat":48.72394,"lon":-123.50913,"speed_ms":0.386,"direction_deg":315.6},{"lat":48.7176,"lon":-123.52163,"speed_ms":0.377,"direction_deg":319.1},{"lat":48.70869,"lon":-123.52171,"speed_ms":0.315,"direction_deg":314.7},{"lat":48.7034,"lon":-123.53391,"speed_ms":0.293,"direction_deg":324.8},{"lat":48.69812,"lon":-123.53168,"speed_ms":0.304,"direction_deg":325.4},{"lat":48.69249,"lon":-123.53313,"speed_ms":0.206,"direction_deg":329.3},{"lat":48.95459,"lon":-123.43619,"speed_ms":0.243,"direction_deg":306.5},{"lat":48.95328,"lon":-123.41721,"speed_ms":0.247,"direction_deg":306.7},{"lat":48.94727,"lon":-123.39437,"speed_ms":0.262,"direction_deg":308.2},{"lat":48.94563,"lon":-123.36477,"speed_ms":0.292,"direction_deg":306.3},{"lat":48.95939,"lon":-123.34576,"speed_ms":0.305,"direction_deg":309.1},{"lat":48.82205,"lon":-123.34088,"speed_ms":0.619,"direction_deg":357.5},{"lat":48.81683,"lon":-123.35242,"speed_ms":0.334,"direction_deg":12.6},{"lat":48.8129,"lon":-123.35435,"speed_ms":0.357,"direction_deg":23.0},{"lat":48.81757,"lon":-123.36044,"speed_ms":0.224,"direction_deg":29.2},{"lat":48.8108,"lon":-123.36548,"speed_ms":0.256,"direction_deg":311.7},{"lat":48.80862,"lon":-123.38054,"speed_ms":0.636,"direction_deg":303.9},{"lat":48.80259,"lon":-123.38515,"speed_ms":0.619,"direction_deg":304.4},{"lat":48.79815,"lon":-123.39049,"speed_ms":0.462,"direction_deg":308.4},{"lat":48.79342,"lon":-123.38781,"speed_ms":0.583,"direction_deg":322.2},{"lat":48.72896,"lon":-123.51526,"speed_ms":0.393,"direction_deg":312.7},{"lat":48.72578,"lon":-123.52362,"speed_ms":0.403,"direction_deg":318.0},{"lat":48.72034,"lon":-123.53172,"speed_ms":0.435,"direction_deg":318.8},{"lat":48.7127,"lon":-123.53546,"speed_ms":0.378,"direction_deg":329.3},{"lat":48.7016,"lon":-123.54403,"speed_ms":0.261,"direction_deg":332.1},{"lat":48.68736,"lon":-123.53316,"speed_ms":0.17,"direction_deg":336.7},{"lat":48.95691,"lon":-123.47923,"speed_ms":0.178,"direction_deg":305.8},{"lat":48.95496,"lon":-123.46928,"speed_ms":0.202,"direction_deg":302.3},{"lat":48.95716,"lon":-123.46038,"speed_ms":0.215,"direction_deg":305.4},{"lat":48.95198,"lon":-123.45187,"speed_ms":0.242,"direction_deg":305.1},{"lat":48.94696,"lon":-123.44291,"speed_ms":0.248,"direction_deg":305.1},{"lat":48.94457,"lon":-123.43028,"speed_ms":0.249,"direction_deg":305.0},{"lat":48.94174,"lon":-123.41461,"speed_ms":0.252,"direction_deg":306.0},{"lat":48.93323,"lon":-123.40358,"speed_ms":0.266,"direction_deg":305.7},{"lat":48.93076,"lon":-123.3798,"speed_ms":0.277,"direction_deg":301.7},{"lat":48.93083,"lon":-123.35471,"speed_ms":0.333,"direction_deg":303.4},{"lat":48.94238,"lon":-123.33824,"speed_ms":0.337,"direction_deg":305.3},{"lat":48.8326,"lon":-123.34223,"speed_ms":0.739,"direction_deg":343.6},{"lat":48.82281,"lon":-123.35695,"speed_ms":0.325,"direction_deg":3.3},{"lat":48.82086,"lon":-123.35979,"speed_ms":0.329,"direction_deg":335.1},{"lat":48.81389,"lon":-123.38885,"speed_ms":0.515,"direction_deg":313.0},{"lat":48.80741,"lon":-123.38963,"speed_ms":0.634,"direction_deg":302.1},{"lat":48.80335,"lon":-123.39333,"speed_ms":0.606,"direction_deg":300.9},{"lat":48.73272,"lon":-123.52108,"speed_ms":0.293,"direction_deg":321.9},{"lat":48.73098,"lon":-123.52944,"speed_ms":0.408,"direction_deg":317.0},{"lat":48.7257,"lon":-123.53567,"speed_ms":0.422,"direction_deg":317.0},{"lat":48.71911,"lon":-123.54227,"speed_ms":0.424,"direction_deg":329.0},{"lat":48.7127,"lon":-123.54882,"speed_ms":0.312,"direction_deg":339.3},{"lat":48.95198,"lon":-123.46209,"speed_ms":0.226,"direction_deg":302.8},{"lat":48.94912,"lon":-123.46874,"speed_ms":0.17,"direction_deg":309.9},{"lat":48.9461,"lon":-123.45972,"speed_ms":0.185,"direction_deg":312.3},{"lat":48.9431,"lon":-123.45206,"speed_ms":0.193,"direction_deg":312.2},{"lat":48.94008,"lon":-123.44295,"speed_ms":0.19,"direction_deg":312.4},{"lat":48.93605,"lon":-123.43376,"speed_ms":0.187,"direction_deg":313.3},{"lat":48.93783,"lon":-123.42422,"speed_ms":0.252,"direction_deg":306.4},{"lat":48.93461,"lon":-123.41668,"speed_ms":0.267,"direction_deg":307.4},{"lat":48.92802,"lon":-123.4156,"speed_ms":0.195,"direction_deg":313.9},{"lat":48.92304,"lon":-123.40784,"speed_ms":0.189,"direction_deg":309.6},{"lat":48.9261,"lon":-123.39538,"speed_ms":0.251,"direction_deg":301.6},{"lat":48.9218,"lon":-123.38673,"speed_ms":0.26,"direction_deg":303.4},{"lat":48.91962,"lon":-123.37484,"speed_ms":0.289,"direction_deg":302.0},{"lat":48.92279,"lon":-123.36452,"speed_ms":0.317,"direction_deg":301.2},{"lat":48.91768,"lon":-123.34974,"speed_ms":0.393,"direction_deg":300.4},{"lat":48.83976,"lon":-123.34005,"speed_ms":0.708,"direction_deg":333.9},{"lat":48.83774,"lon":-123.35049,"speed_ms":0.672,"direction_deg":327.9},{"lat":48.83416,"lon":-123.35447,"speed_ms":0.802,"direction_deg":341.4},{"lat":48.82046,"lon":-123.39185,"speed_ms":0.541,"direction_deg":317.2},{"lat":48.8186,"lon":-123.4005,"speed_ms":0.568,"direction_deg":317.0},{"lat":48.80914,"lon":-123.39931,"speed_ms":0.52,"direction_deg":302.7},{"lat":48.80733,"lon":-123.41102,"speed_ms":0.386,"direction_deg":306.4},{"lat":48.80096,"lon":-123.41146,"speed_ms":0.343,"direction_deg":305.7},{"lat":48.73688,"lon":-123.52734,"speed_ms":0.355,"direction_deg":314.2},{"lat":48.73304,"lon":-123.53922,"speed_ms":0.379,"direction_deg":311.9},{"lat":48.72505,"lon":-123.54778,"speed_ms":0.392,"direction_deg":318.1},{"lat":48.71775,"lon":-123.55327,"speed_ms":0.322,"direction_deg":331.2},{"lat":48.93204,"lon":-123.42467,"speed_ms":0.196,"direction_deg":314.2},{"lat":48.9211,"lon":-123.39868,"speed_ms":0.192,"direction_deg":303.7},{"lat":48.91806,"lon":-123.3895,"speed_ms":0.195,"direction_deg":306.1},{"lat":48.91505,"lon":-123.38193,"speed_ms":0.202,"direction_deg":307.2},{"lat":48.91207,"lon":-123.37136,"speed_ms":0.207,"direction_deg":304.9},{"lat":48.91549,"lon":-123.36347,"speed_ms":0.328,"direction_deg":297.2},{"lat":48.90915,"lon":-123.35466,"speed_ms":0.246,"direction_deg":300.8},{"lat":48.90715,"lon":-123.34408,"speed_ms":0.273,"direction_deg":303.4},{"lat":48.84654,"lon":-123.33786,"speed_ms":0.496,"direction_deg":333.7},{"lat":48.84278,"lon":-123.34675,"speed_ms":0.563,"direction_deg":324.6},{"lat":48.84214,"lon":-123.35572,"speed_ms":0.504,"direction_deg":318.4},{"lat":48.83411,"lon":-123.36146,"speed_ms":0.412,"direction_deg":324.2},{"lat":48.82329,"lon":-123.39066,"speed_ms":0.513,"direction_deg":310.6},{"lat":48.8262,"lon":-123.39656,"speed_ms":0.459,"direction_deg":322.2},{"lat":48.82543,"lon":-123.40551,"speed_ms":0.546,"direction_deg":337.9},{"lat":48.82001,"lon":-123.4112,"speed_ms":0.51,"direction_deg":331.3},{"lat":48.81398,"lon":-123.40807,"speed_ms":0.458,"direction_deg":315.9},{"lat":48.81479,"lon":-123.41799,"speed_ms":0.427,"direction_deg":322.0},{"lat":48.80485,"lon":-123.4174,"speed_ms":0.292,"direction_deg":310.7},{"lat":48.73993,"lon":-123.53348,"speed_ms":0.372,"direction_deg":309.8},{"lat":48.74005,"lon":-123.5455,"speed_ms":0.443,"direction_deg":318.9},{"lat":48.7325,"lon":-123.55552,"speed_ms":0.368,"direction_deg":318.5},{"lat":48.72161,"lon":-123.56075,"speed_ms":0.257,"direction_deg":327.5},{"lat":48.91114,"lon":-123.3652,"speed_ms":0.212,"direction_deg":298.1},{"lat":48.90412,"lon":-123.33958,"speed_ms":0.287,"direction_deg":310.2},{"lat":48.8529,"lon":-123.33528,"speed_ms":0.302,"direction_deg":327.1},{"lat":48.85297,"lon":-123.34449,"speed_ms":0.535,"direction_deg":338.7},{"lat":48.84795,"lon":-123.34974,"speed_ms":0.461,"direction_deg":334.1},{"lat":48.84849,"lon":-123.36088,"speed_ms":0.393,"direction_deg":323.1},{"lat":48.84201,"lon":-123.36563,"speed_ms":0.409,"direction_deg":321.6},{"lat":48.83184,"lon":-123.4099,"speed_ms":0.541,"direction_deg":351.4},{"lat":48.82588,"lon":-123.41519,"speed_ms":0.482,"direction_deg":342.6},{"lat":48.82097,"lon":-123.41909,"speed_ms":0.416,"direction_deg":336.9},{"lat":48.81908,"lon":-123.42637,"speed_ms":0.336,"direction_deg":329.0},{"lat":48.74378,"lon":-123.55646,"speed_ms":0.459,"direction_deg":330.5},{"lat":48.73688,"lon":-123.56799,"speed_ms":0.296,"direction_deg":332.0},{"lat":48.72657,"lon":-123.56829,"speed_ms":0.236,"direction_deg":327.0},{"lat":48.85607,"lon":-123.34166,"speed_ms":0.382,"direction_deg":345.6},{"lat":48.8582,"lon":-123.34681,"speed_ms":0.791,"direction_deg":17.4},{"lat":48.85476,"lon":-123.35424,"speed_ms":0.384,"direction_deg":345.7},{"lat":48.85596,"lon":-123.36715,"speed_ms":0.302,"direction_deg":314.5},{"lat":48.84745,"lon":-123.37354,"speed_ms":0.4,"direction_deg":307.6},{"lat":48.84231,"lon":-123.37188,"speed_ms":0.358,"direction_deg":312.6},{"lat":48.83927,"lon":-123.40931,"speed_ms":0.54,"direction_deg":353.1},{"lat":48.83705,"lon":-123.41798,"speed_ms":0.393,"direction_deg":15.9},{"lat":48.83107,"lon":-123.42106,"speed_ms":0.354,"direction_deg":356.0},{"lat":48.82516,"lon":-123.42446,"speed_ms":0.332,"direction_deg":342.3},{"lat":48.82331,"lon":-123.4336,"speed_ms":0.257,"direction_deg":331.4},{"lat":48.81686,"lon":-123.43585,"speed_ms":0.317,"direction_deg":322.7},{"lat":48.75082,"lon":-123.54884,"speed_ms":0.347,"direction_deg":332.8},{"lat":48.75158,"lon":-123.56043,"speed_ms":0.778,"direction_deg":341.4},{"lat":48.73336,"lon":-123.58056,"speed_ms":0.182,"direction_deg":341.2},{"lat":48.85988,"lon":-123.34146,"speed_ms":0.993,"direction_deg":78.7},{"lat":48.86267,"lon":-123.34464,"speed_ms":1.454,"direction_deg":41.0},{"lat":48.8599,"lon":-123.35144,"speed_ms":0.624,"direction_deg":29.1},{"lat":48.86158,"lon":-123.3587,"speed_ms":0.202,"direction_deg":18.2},{"lat":48.86357,"lon":-123.36715,"speed_ms":0.184,"direction_deg":340.3},{"lat":48.86072,"lon":-123.37547,"speed_ms":0.372,"direction_deg":313.8},{"lat":48.85465,"lon":-123.38092,"speed_ms":0.435,"direction_deg":303.6},{"lat":48.84599,"lon":-123.38841,"speed_ms":0.306,"direction_deg":306.2},{"lat":48.83904,"lon":-123.40111,"speed_ms":0.389,"direction_deg":356.2},{"lat":48.84404,"lon":-123.40571,"speed_ms":0.387,"direction_deg":2.1},{"lat":48.8447,"lon":-123.41227,"speed_ms":0.577,"direction_deg":355.2},{"lat":48.84238,"lon":-123.41698,"speed_ms":0.47,"direction_deg":20.5},{"lat":48.83673,"lon":-123.42737,"speed_ms":0.266,"direction_deg":30.8},{"lat":48.83017,"lon":-123.43196,"speed_ms":0.228,"direction_deg":352.5},{"lat":48.82151,"lon":-123.44318,"speed_ms":0.178,"direction_deg":330.9},{"lat":48.75501,"lon":-123.55349,"speed_ms":0.421,"direction_deg":327.9},{"lat":48.75756,"lon":-123.56473,"speed_ms":1.095,"direction_deg":333.8},{"lat":48.75229,"lon":-123.56898,"speed_ms":0.53,"direction_deg":337.9},{"lat":48.86158,"lon":-123.32759,"speed_ms":2.185,"direction_deg":100.3},{"lat":48.86473,"lon":-123.33842,"speed_ms":1.586,"direction_deg":73.5},{"lat":48.86293,"lon":-123.35109,"speed_ms":0.735,"direction_deg":48.7},{"lat":48.86605,"lon":-123.37643,"speed_ms":0.34,"direction_deg":318.8},{"lat":48.86253,"lon":-123.38665,"speed_ms":0.505,"direction_deg":313.7},{"lat":48.85448,"lon":-123.39369,"speed_ms":0.429,"direction_deg":306.6},{"lat":48.84419,"lon":-123.39813,"speed_ms":0.436,"direction_deg":14.4},{"lat":48.85076,"lon":-123.40246,"speed_ms":0.28,"direction_deg":349.3},{"lat":48.84997,"lon":-123.41133,"speed_ms":0.534,"direction_deg":346.5},{"lat":48.84673,"lon":-123.41791,"speed_ms":0.622,"direction_deg":2.6},{"lat":48.84532,"lon":-123.42082,"speed_ms":0.492,"direction_deg":35.7},{"lat":48.84477,"lon":-123.42584,"speed_ms":0.276,"direction_deg":29.1},{"lat":48.84387,"lon":-123.4312,"speed_ms":0.172,"direction_deg":69.4},{"lat":48.75937,"lon":-123.55842,"speed_ms":0.568,"direction_deg":330.5},{"lat":48.76302,"lon":-123.56819,"speed_ms":1.283,"direction_deg":345.2},{"lat":48.75792,"lon":-123.57395,"speed_ms":0.763,"direction_deg":339.0},{"lat":48.96254,"lon":-123.58084,"speed_ms":0.39,"direction_deg":313.5},{"lat":48.86842,"lon":-123.33266,"speed_ms":1.124,"direction_deg":86.6},{"lat":48.87003,"lon":-123.34455,"speed_ms":0.912,"direction_deg":56.8},{"lat":48.87014,"lon":-123.38575,"speed_ms":0.383,"direction_deg":321.4},{"lat":48.86928,"lon":-123.39578,"speed_ms":0.495,"direction_deg":321.7},{"lat":48.86133,"lon":-123.39688,"speed_ms":0.45,"direction_deg":318.8},{"lat":48.85677,"lon":-123.40507,"speed_ms":0.417,"direction_deg":329.9},{"lat":48.85551,"lon":-123.41641,"speed_ms":0.505,"direction_deg":330.3},{"lat":48.85062,"lon":-123.41965,"speed_ms":0.588,"direction_deg":341.9},{"lat":48.76387,"lon":-123.56287,"speed_ms":0.722,"direction_deg":355.7},{"lat":48.77,"lon":-123.56895,"speed_ms":1.255,"direction_deg":10.0},{"lat":48.76307,"lon":-123.57665,"speed_ms":0.795,"direction_deg":352.2},{"lat":48.96154,"lon":-123.57777,"speed_ms":0.395,"direction_deg":313.5},{"lat":48.87509,"lon":-123.38873,"speed_ms":0.362,"direction_deg":329.8},{"lat":48.87439,"lon":-123.40342,"speed_ms":0.439,"direction_deg":321.0},{"lat":48.86861,"lon":-123.40698,"speed_ms":0.461,"direction_deg":323.1},{"lat":48.86369,"lon":-123.40343,"speed_ms":0.459,"direction_deg":321.2},{"lat":48.86271,"lon":-123.41331,"speed_ms":0.468,"direction_deg":326.2},{"lat":48.85981,"lon":-123.42377,"speed_ms":0.563,"direction_deg":321.7},{"lat":48.8535,"lon":-123.42581,"speed_ms":0.558,"direction_deg":324.7},{"lat":48.76903,"lon":-123.56079,"speed_ms":0.787,"direction_deg":17.9},{"lat":48.77442,"lon":-123.56065,"speed_ms":1.364,"direction_deg":36.8},{"lat":48.77746,"lon":-123.56883,"speed_ms":1.028,"direction_deg":36.4},{"lat":48.77263,"lon":-123.5763,"speed_ms":0.637,"direction_deg":9.5},{"lat":48.76737,"lon":-123.57957,"speed_ms":0.547,"direction_deg":357.4},{"lat":48.95944,"lon":-123.60857,"speed_ms":0.315,"direction_deg":324.0},{"lat":48.9585,"lon":-123.61985,"speed_ms":0.326,"direction_deg":340.4},{"lat":48.95377,"lon":-123.56304,"speed_ms":0.534,"direction_deg":314.0},{"lat":48.9589,"lon":-123.55254,"speed_ms":0.595,"direction_deg":311.1},{"lat":48.87935,"lon":-123.38745,"speed_ms":0.459,"direction_deg":342.9},{"lat":48.88152,"lon":-123.39665,"speed_ms":0.523,"direction_deg":339.6},{"lat":48.88022,"lon":-123.40247,"speed_ms":0.398,"direction_deg":312.1},{"lat":48.87797,"lon":-123.40902,"speed_ms":0.435,"direction_deg":313.2},{"lat":48.87345,"lon":-123.4122,"speed_ms":0.469,"direction_deg":319.9},{"lat":48.8688,"lon":-123.41542,"speed_ms":0.492,"direction_deg":322.9},{"lat":48.86627,"lon":-123.42269,"speed_ms":0.534,"direction_deg":321.1},{"lat":48.86361,"lon":-123.43251,"speed_ms":0.563,"direction_deg":316.8},{"lat":48.85618,"lon":-123.43154,"speed_ms":0.417,"direction_deg":318.9},{"lat":48.77289,"lon":-123.55433,"speed_ms":0.778,"direction_deg":33.7},{"lat":48.77925,"lon":-123.55569,"speed_ms":1.403,"direction_deg":39.4},{"lat":48.78199,"lon":-123.56288,"speed_ms":0.884,"direction_deg":45.9},{"lat":48.95736,"lon":-123.6266,"speed_ms":0.349,"direction_deg":341.8},{"lat":48.95303,"lon":-123.6138,"speed_ms":0.191,"direction_deg":324.3},{"lat":48.95174,"lon":-123.60286,"speed_ms":0.229,"direction_deg":295.9},{"lat":48.9578,"lon":-123.59758,"speed_ms":0.301,"direction_deg":303.6},{"lat":48.95091,"lon":-123.62474,"speed_ms":0.183,"direction_deg":337.8},{"lat":48.96136,"lon":-123.59126,"speed_ms":0.301,"direction_deg":313.6},{"lat":48.94942,"lon":-123.55482,"speed_ms":0.358,"direction_deg":310.6},{"lat":48.9595,"lon":-123.5411,"speed_ms":0.375,"direction_deg":312.6},{"lat":48.953,"lon":-123.54521,"speed_ms":0.667,"direction_deg":309.7},{"lat":48.88458,"lon":-123.39372,"speed_ms":0.544,"direction_deg":333.7},{"lat":48.88344,"lon":-123.41054,"speed_ms":0.51,"direction_deg":310.5},{"lat":48.87852,"lon":-123.41691,"speed_ms":0.501,"direction_deg":313.5},{"lat":48.87295,"lon":-123.42196,"speed_ms":0.522,"direction_deg":318.0},{"lat":48.86949,"lon":-123.42984,"speed_ms":0.55,"direction_deg":316.8},{"lat":48.86983,"lon":-123.43954,"speed_ms":0.532,"direction_deg":312.3},{"lat":48.86335,"lon":-123.444,"speed_ms":0.495,"direction_deg":311.7},{"lat":48.85925,"lon":-123.43621,"speed_ms":0.444,"direction_deg":312.4},{"lat":48.77562,"lon":-123.54706,"speed_ms":0.648,"direction_deg":25.9},{"lat":48.78295,"lon":-123.55048,"speed_ms":1.172,"direction_deg":12.3},{"lat":48.78355,"lon":-123.55566,"speed_ms":0.994,"direction_deg":24.6},{"lat":48.95315,"lon":-123.59177,"speed_ms":0.377,"direction_deg":289.0},{"lat":48.95772,"lon":-123.59099,"speed_ms":0.303,"direction_deg":303.0},{"lat":48.95842,"lon":-123.58341,"speed_ms":0.29,"direction_deg":299.0},{"lat":48.9449,"lon":-123.54649,"speed_ms":0.616,"direction_deg":314.5},{"lat":48.95558,"lon":-123.53516,"speed_ms":0.431,"direction_deg":309.0},{"lat":48.94777,"lon":-123.53638,"speed_ms":0.723,"direction_deg":310.6},{"lat":48.88883,"lon":-123.39761,"speed_ms":0.233,"direction_deg":330.3},{"lat":48.88819,"lon":-123.41771,"speed_ms":0.373,"direction_deg":316.6},{"lat":48.88403,"lon":-123.42145,"speed_ms":0.548,"direction_deg":314.9},{"lat":48.87938,"lon":-123.42641,"speed_ms":0.535,"direction_deg":315.3},{"lat":48.87478,"lon":-123.43222,"speed_ms":0.539,"direction_deg":314.9},{"lat":48.87606,"lon":-123.44006,"speed_ms":0.519,"direction_deg":315.7},{"lat":48.87459,"lon":-123.44811,"speed_ms":0.498,"direction_deg":313.6},{"lat":48.86728,"lon":-123.45143,"speed_ms":0.447,"direction_deg":311.3},{"lat":48.78043,"lon":-123.54294,"speed_ms":0.56,"direction_deg":0.7},{"lat":48.78653,"lon":-123.5477,"speed_ms":0.943,"direction_deg":353.6},{"lat":48.78873,"lon":-123.55444,"speed_ms":1.466,"direction_deg":355.2},{"lat":48.78862,"lon":-123.55982,"speed_ms":0.973,"direction_deg":356.3},{"lat":48.95146,"lon":-123.58276,"speed_ms":0.427,"direction_deg":296.2},{"lat":48.95742,"lon":-123.57585,"speed_ms":0.298,"direction_deg":299.7},{"lat":48.94066,"lon":-123.54003,"speed_ms":0.506,"direction_deg":314.8},{"lat":48.95163,"lon":-123.52623,"speed_ms":0.471,"direction_deg":305.3},{"lat":48.9413,"lon":-123.5308,"speed_ms":0.694,"direction_deg":310.3},{"lat":48.94604,"lon":-123.52711,"speed_ms":0.722,"direction_deg":308.0},{"lat":48.8971,"lon":-123.40212,"speed_ms":0.295,"direction_deg":311.4},{"lat":48.89357,"lon":-123.42585,"speed_ms":0.553,"direction_deg":315.8},{"lat":48.88885,"lon":-123.42615,"speed_ms":0.548,"direction_deg":315.2},{"lat":48.88521,"lon":-123.43083,"speed_ms":0.533,"direction_deg":315.9},{"lat":48.88049,"lon":-123.436,"speed_ms":0.529,"direction_deg":317.0},{"lat":48.88085,"lon":-123.44554,"speed_ms":0.517,"direction_deg":317.1},{"lat":48.88024,"lon":-123.45661,"speed_ms":0.505,"direction_deg":317.7},{"lat":48.87333,"lon":-123.45609,"speed_ms":0.466,"direction_deg":313.6},{"lat":48.87129,"lon":-123.45903,"speed_ms":0.448,"direction_deg":309.9},{"lat":48.79032,"lon":-123.55174,"speed_ms":0.871,"direction_deg":9.9},{"lat":48.7919,"lon":-123.55775,"speed_ms":0.895,"direction_deg":355.1},{"lat":48.79153,"lon":-123.56423,"speed_ms":0.592,"direction_deg":2.9},{"lat":48.95046,"lon":-123.57418,"speed_ms":0.436,"direction_deg":301.7},{"lat":48.95533,"lon":-123.5697,"speed_ms":0.273,"direction_deg":307.0},{"lat":48.93687,"lon":-123.53434,"speed_ms":0.628,"direction_deg":312.5},{"lat":48.94759,"lon":-123.52008,"speed_ms":0.458,"direction_deg":304.3},{"lat":48.94125,"lon":-123.52068,"speed_ms":0.704,"direction_deg":303.3},{"lat":48.93487,"lon":-123.52561,"speed_ms":0.601,"direction_deg":304.6},{"lat":48.89711,"lon":-123.40843,"speed_ms":0.329,"direction_deg":323.3},{"lat":48.89212,"lon":-123.43429,"speed_ms":0.526,"direction_deg":315.2},{"lat":48.88654,"lon":-123.44051,"speed_ms":0.526,"direction_deg":314.9},{"lat":48.8874,"lon":-123.45108,"speed_ms":0.53,"direction_deg":315.6},{"lat":48.88843,"lon":-123.46158,"speed_ms":0.549,"direction_deg":313.9},{"lat":48.88312,"lon":-123.46831,"speed_ms":0.438,"direction_deg":313.7},{"lat":48.79462,"lon":-123.55359,"speed_ms":0.8,"direction_deg":10.0},{"lat":48.79673,"lon":-123.56118,"speed_ms":0.311,"direction_deg":357.4},{"lat":48.94501,"lon":-123.56884,"speed_ms":0.526,"direction_deg":307.9},{"lat":48.94458,"lon":-123.51248,"speed_ms":0.457,"direction_deg":300.9},{"lat":48.93392,"lon":-123.51429,"speed_ms":0.647,"direction_deg":302.4},{"lat":48.93971,"lon":-123.51121,"speed_ms":0.644,"direction_deg":300.4},{"lat":48.92888,"lon":-123.52777,"speed_ms":0.581,"direction_deg":299.6},{"lat":48.92961,"lon":-123.52029,"speed_ms":0.597,"direction_deg":302.9},{"lat":48.90094,"lon":-123.40678,"speed_ms":0.259,"direction_deg":329.4},{"lat":48.89924,"lon":-123.41488,"speed_ms":0.245,"direction_deg":323.1},{"lat":48.9029,"lon":-123.42366,"speed_ms":0.252,"direction_deg":335.4},{"lat":48.90354,"lon":-123.43433,"speed_ms":0.351,"direction_deg":334.5},{"lat":48.89866,"lon":-123.44011,"speed_ms":0.482,"direction_deg":323.6},{"lat":48.89323,"lon":-123.44544,"speed_ms":0.538,"direction_deg":313.5},{"lat":48.89487,"lon":-123.45637,"speed_ms":0.549,"direction_deg":312.4},{"lat":48.89441,"lon":-123.46658,"speed_ms":0.578,"direction_deg":310.2},{"lat":48.88962,"lon":-123.46973,"speed_ms":0.536,"direction_deg":312.0},{"lat":48.88812,"lon":-123.47687,"speed_ms":0.488,"direction_deg":311.3},{"lat":48.88345,"lon":-123.47917,"speed_ms":0.514,"direction_deg":311.3},{"lat":48.7927,"lon":-123.53785,"speed_ms":0.169,"direction_deg":63.8},{"lat":48.79901,"lon":-123.54287,"speed_ms":0.232,"direction_deg":353.1},{"lat":48.79851,"lon":-123.55258,"speed_ms":0.37,"direction_deg":351.9},{"lat":48.80278,"lon":-123.5601,"speed_ms":0.431,"direction_deg":336.6},{"lat":48.94742,"lon":-123.55935,"speed_ms":0.361,"direction_deg":310.8},{"lat":48.93942,"lon":-123.55912,"speed_ms":0.557,"direction_deg":307.9},{"lat":48.93659,"lon":-123.54,"speed_ms":0.49,"direction_deg":305.2},{"lat":48.9283,"lon":-123.53843,"speed_ms":0.526,"direction_deg":300.8},{"lat":48.94251,"lon":-123.50472,"speed_ms":0.418,"direction_deg":299.3},{"lat":48.93536,"lon":-123.5027,"speed_ms":0.619,"direction_deg":299.3},{"lat":48.92692,"lon":-123.51322,"speed_ms":0.584,"direction_deg":307.8},{"lat":48.92838,"lon":-123.50495,"speed_ms":0.616,"direction_deg":305.7},{"lat":48.9235,"lon":-123.53018,"speed_ms":0.589,"direction_deg":303.3},{"lat":48.9236,"lon":-123.52034,"speed_ms":0.53,"direction_deg":304.9},{"lat":48.90596,"lon":-123.41268,"speed_ms":0.234,"direction_deg":319.9},{"lat":48.91006,"lon":-123.42043,"speed_ms":0.277,"direction_deg":319.3},{"lat":48.90799,"lon":-123.42862,"speed_ms":0.338,"direction_deg":320.9},{"lat":48.91008,"lon":-123.43746,"speed_ms":0.427,"direction_deg":316.4},{"lat":48.89947,"lon":-123.44993,"speed_ms":0.544,"direction_deg":316.4},{"lat":48.90019,"lon":-123.45646,"speed_ms":0.55,"direction_deg":314.2},{"lat":48.90077,"lon":-123.4637,"speed_ms":0.59,"direction_deg":313.5},{"lat":48.89887,"lon":-123.47233,"speed_ms":0.601,"direction_deg":312.8},{"lat":48.89389,"lon":-123.47535,"speed_ms":0.566,"direction_deg":310.8},{"lat":48.89223,"lon":-123.48403,"speed_ms":0.478,"direction_deg":315.9},{"lat":48.88626,"lon":-123.4848,"speed_ms":0.406,"direction_deg":312.3},{"lat":48.80545,"lon":-123.54257,"speed_ms":0.196,"direction_deg":343.7},{"lat":48.80579,"lon":-123.55099,"speed_ms":0.304,"direction_deg":328.2},{"lat":48.80934,"lon":-123.56041,"speed_ms":0.348,"direction_deg":312.5},{"lat":48.80356,"lon":-123.56971,"speed_ms":0.205,"direction_deg":328.3},{"lat":48.92501,"lon":-123.6278,"speed_ms":0.257,"direction_deg":330.9},{"lat":48.92322,"lon":-123.63252,"speed_ms":0.235,"direction_deg":321.7},{"lat":48.91401,"lon":-123.63025,"speed_ms":0.212,"direction_deg":312.3},{"lat":48.90295,"lon":-123.62928,"speed_ms":0.2,"direction_deg":312.0},{"lat":48.94343,"lon":-123.5533,"speed_ms":0.374,"direction_deg":310.0},{"lat":48.93035,"lon":-123.55634,"speed_ms":0.361,"direction_deg":310.4},{"lat":48.93405,"lon":-123.54846,"speed_ms":0.537,"direction_deg":305.9},{"lat":48.92837,"lon":-123.54811,"speed_ms":0.438,"direction_deg":308.3},{"lat":48.92232,"lon":-123.54559,"speed_ms":0.352,"direction_deg":304.0},{"lat":48.91939,"lon":-123.53666,"speed_ms":0.405,"direction_deg":304.2},{"lat":48.93945,"lon":-123.49541,"speed_ms":0.387,"direction_deg":300.7},{"lat":48.92907,"lon":-123.49463,"speed_ms":0.561,"direction_deg":305.6},{"lat":48.93397,"lon":-123.4917,"speed_ms":0.547,"direction_deg":301.5},{"lat":48.92275,"lon":-123.50718,"speed_ms":0.603,"direction_deg":309.7},{"lat":48.92264,"lon":-123.51318,"speed_ms":0.544,"direction_deg":308.9},{"lat":48.92309,"lon":-123.49705,"speed_ms":0.513,"direction_deg":312.1},{"lat":48.91661,"lon":-123.52647,"speed_ms":0.543,"direction_deg":309.1},{"lat":48.91741,"lon":-123.51324,"speed_ms":0.644,"direction_deg":309.1},{"lat":48.9132,"lon":-123.42657,"speed_ms":0.317,"direction_deg":309.9},{"lat":48.91629,"lon":-123.4343,"speed_ms":0.352,"direction_deg":306.7},{"lat":48.91562,"lon":-123.44666,"speed_ms":0.487,"direction_deg":306.1},{"lat":48.90937,"lon":-123.44743,"speed_ms":0.375,"direction_deg":319.3},{"lat":48.90557,"lon":-123.45593,"speed_ms":0.582,"direction_deg":317.7},{"lat":48.90601,"lon":-123.46465,"speed_ms":0.589,"direction_deg":317.2},{"lat":48.90577,"lon":-123.47365,"speed_ms":0.576,"direction_deg":315.5},{"lat":48.8995,"lon":-123.48203,"speed_ms":0.566,"direction_deg":314.0},{"lat":48.8136,"lon":-123.55298,"speed_ms":0.217,"direction_deg":329.1},{"lat":48.81227,"lon":-123.5685,"speed_ms":0.3,"direction_deg":310.1},{"lat":48.80548,"lon":-123.57724,"speed_ms":0.171,"direction_deg":329.8},{"lat":48.92987,"lon":-123.63079,"speed_ms":0.195,"direction_deg":334.6},{"lat":48.92995,"lon":-123.64276,"speed_ms":0.188,"direction_deg":321.8},{"lat":48.91777,"lon":-123.64394,"speed_ms":0.202,"direction_deg":317.2},{"lat":48.90618,"lon":-123.64267,"speed_ms":0.202,"direction_deg":310.8},{"lat":48.89066,"lon":-123.63221,"speed_ms":0.17,"direction_deg":334.6},{"lat":48.92637,"lon":-123.55184,"speed_ms":0.386,"direction_deg":313.2},{"lat":48.93642,"lon":-123.48925,"speed_ms":0.377,"direction_deg":302.4},{"lat":48.92365,"lon":-123.48531,"speed_ms":0.551,"direction_deg":307.4},{"lat":48.92975,"lon":-123.48637,"speed_ms":0.54,"direction_deg":304.2},{"lat":48.93341,"lon":-123.4802,"speed_ms":0.38,"direction_deg":302.4},{"lat":48.91736,"lon":-123.50104,"speed_ms":0.564,"direction_deg":310.4},{"lat":48.91733,"lon":-123.49097,"speed_ms":0.548,"direction_deg":310.7},{"lat":48.91253,"lon":-123.52023,"speed_ms":0.503,"direction_deg":310.4},{"lat":48.91128,"lon":-123.50291,"speed_ms":0.532,"direction_deg":313.2},{"lat":48.91055,"lon":-123.51116,"speed_ms":0.514,"direction_deg":313.0},{"lat":48.91934,"lon":-123.44206,"speed_ms":0.373,"direction_deg":303.8},{"lat":48.92244,"lon":-123.44987,"speed_ms":0.428,"direction_deg":301.7},{"lat":48.91856,"lon":-123.4584,"speed_ms":0.515,"direction_deg":306.4},{"lat":48.91209,"lon":-123.45472,"speed_ms":0.474,"direction_deg":314.9},{"lat":48.91155,"lon":-123.46451,"speed_ms":0.564,"direction_deg":314.2},{"lat":48.91399,"lon":-123.47508,"speed_ms":0.579,"direction_deg":311.9},{"lat":48.9108,"lon":-123.48466,"speed_ms":0.546,"direction_deg":312.6},{"lat":48.90522,"lon":-123.48335,"speed_ms":0.55,"direction_deg":314.7},{"lat":48.90488,"lon":-123.49353,"speed_ms":0.536,"direction_deg":312.8},{"lat":48.8984,"lon":-123.5018,"speed_ms":0.46,"direction_deg":311.7},{"lat":48.81973,"lon":-123.56694,"speed_ms":0.286,"direction_deg":339.7},{"lat":48.81678,"lon":-123.57799,"speed_ms":0.252,"direction_deg":331.3},{"lat":48.8085,"lon":-123.58486,"speed_ms":0.175,"direction_deg":329.0},{"lat":48.93933,"lon":-123.64888,"speed_ms":0.184,"direction_deg":318.0},{"lat":48.93302,"lon":-123.65793,"speed_ms":0.194,"direction_deg":316.4},{"lat":48.92238,"lon":-123.65854,"speed_ms":0.203,"direction_deg":316.8},{"lat":48.91073,"lon":-123.6567,"speed_ms":0.192,"direction_deg":316.8},{"lat":48.88556,"lon":-123.63271,"speed_ms":0.178,"direction_deg":359.3},{"lat":48.91948,"lon":-123.47692,"speed_ms":0.526,"direction_deg":308.2},{"lat":48.92486,"lon":-123.47331,"speed_ms":0.496,"direction_deg":304.8},{"lat":48.91697,"lon":-123.48251,"speed_ms":0.52,"direction_deg":310.5},{"lat":48.92856,"lon":-123.47948,"speed_ms":0.488,"direction_deg":305.2},{"lat":48.93144,"lon":-123.47265,"speed_ms":0.401,"direction_deg":300.6},{"lat":48.91221,"lon":-123.49437,"speed_ms":0.494,"direction_deg":313.1},{"lat":48.90567,"lon":-123.50526,"speed_ms":0.484,"direction_deg":313.8},{"lat":48.92548,"lon":-123.45904,"speed_ms":0.451,"direction_deg":302.4},{"lat":48.92329,"lon":-123.46481,"speed_ms":0.522,"direction_deg":303.4},{"lat":48.91863,"lon":-123.46858,"speed_ms":0.55,"direction_deg":308.6},{"lat":48.90232,"lon":-123.5077,"speed_ms":0.409,"direction_deg":312.8},{"lat":48.82497,"lon":-123.57179,"speed_ms":0.377,"direction_deg":355.6},{"lat":48.82442,"lon":-123.57989,"speed_ms":0.359,"direction_deg":356.4},{"lat":48.82255,"lon":-123.58567,"speed_ms":0.232,"direction_deg":10.8},{"lat":48.9406,"lon":-123.65854,"speed_ms":0.194,"direction_deg":324.0},{"lat":48.92854,"lon":-123.66771,"speed_ms":0.203,"direction_deg":313.5},{"lat":48.93726,"lon":-123.67089,"speed_ms":0.195,"direction_deg":314.4},{"lat":48.92218,"lon":-123.6724,"speed_ms":0.215,"direction_deg":310.5},{"lat":48.91382,"lon":-123.67028,"speed_ms":0.187,"direction_deg":328.6},{"lat":48.92846,"lon":-123.46504,"speed_ms":0.421,"direction_deg":301.2},{"lat":48.83005,"lon":-123.57035,"speed_ms":0.402,"direction_deg":10.3},{"lat":48.8296,"lon":-123.57875,"speed_ms":0.458,"direction_deg":352.1},{"lat":48.82807,"lon":-123.58402,"speed_ms":0.409,"direction_deg":2.2},{"lat":48.96122,"lon":-123.7015,"speed_ms":0.175,"direction_deg":325.6},{"lat":48.94594,"lon":-123.6629,"speed_ms":0.2,"direction_deg":320.4},{"lat":48.92818,"lon":-123.67986,"speed_ms":0.199,"direction_deg":310.0},{"lat":48.94572,"lon":-123.67325,"speed_ms":0.185,"direction_deg":319.6},{"lat":48.9419,"lon":-123.68365,"speed_ms":0.191,"direction_deg":313.0},{"lat":48.93468,"lon":-123.68489,"speed_ms":0.197,"direction_deg":312.4},{"lat":48.91801,"lon":-123.67773,"speed_ms":0.206,"direction_deg":313.0},{"lat":48.92219,"lon":-123.68095,"speed_ms":0.188,"direction_deg":305.4},{"lat":48.83691,"lon":-123.57034,"speed_ms":0.346,"direction_deg":5.0},{"lat":48.83487,"lon":-123.57871,"speed_ms":0.4,"direction_deg":354.0},{"lat":48.834,"lon":-123.58714,"speed_ms":0.38,"direction_deg":1.6},{"lat":48.95343,"lon":-123.69815,"speed_ms":0.17,"direction_deg":319.0},{"lat":48.95971,"lon":-123.68761,"speed_ms":0.199,"direction_deg":322.3},{"lat":48.95162,"lon":-123.66725,"speed_ms":0.175,"direction_deg":322.9},{"lat":48.92973,"lon":-123.69306,"speed_ms":0.205,"direction_deg":316.6},{"lat":48.9519,"lon":-123.68137,"speed_ms":0.183,"direction_deg":315.9},{"lat":48.94507,"lon":-123.69589,"speed_ms":0.174,"direction_deg":313.3},{"lat":48.93649,"lon":-123.69673,"speed_ms":0.19,"direction_deg":309.4},{"lat":48.91922,"lon":-123.68507,"speed_ms":0.172,"direction_deg":292.0},{"lat":48.85125,"lon":-123.58227,"speed_ms":0.234,"direction_deg":347.3},{"lat":48.84281,"lon":-123.57024,"speed_ms":0.307,"direction_deg":355.1},{"lat":48.83948,"lon":-123.5774,"speed_ms":0.33,"direction_deg":349.2},{"lat":48.83889,"lon":-123.58863,"speed_ms":0.34,"direction_deg":2.5},{"lat":48.84785,"lon":-123.57031,"speed_ms":0.318,"direction_deg":1.4},{"lat":48.85248,"lon":-123.56721,"speed_ms":0.187,"direction_deg":4.1},{"lat":48.84385,"lon":-123.57972,"speed_ms":0.319,"direction_deg":353.6},{"lat":48.84296,"lon":-123.58861,"speed_ms":0.359,"direction_deg":359.7},{"lat":48.84897,"lon":-123.59175,"speed_ms":0.358,"direction_deg":4.1},{"lat":48.94941,"lon":-123.80794,"speed_ms":2.0,"direction_deg":90.8}]